zl2x/__init__.py
zl2x/_aevents.py
zl2x/_client.py
zl2x/_core.py
zl2x/_exception.py
zl2x/_message.py
zl2x/_objects.py
zl2x/_package.py
zl2x/_parse_message.py
zl2x/_state.py
zl2x/_threads.py
zl2x/_util.py
zl2x/logging.py
zl2x/models.py
zl2x/Async/__init__.py
zl2x/Async/_async.py
zl2x/Async/_state.py
zl2x/simple/__init__.py
zl2x/simple/_async.py
zl2x/simple/_state.py
zl2x-1.0.2.dist-info/METADATA
zl2x-1.0.2.dist-info/WHEEL
zl2x-1.0.2.dist-info/top_level.txt
zl2x-1.0.2.dist-info/RECORD
