Metadata-Version: 2.4
Name: zl2x
Version: 1.0.2
Summary: Zalo API for Python
Classifier: Programming Language :: Python :: 3
Classifier: License :: OSI Approved :: MIT License
Classifier: Operating System :: OS Independent
Requires-Dist: requests
Requires-Dist: aiohttp
Requires-Dist: aenum
Requires-Dist: attr
Requires-Dist: pycryptodome
Requires-Dist: datetime
Requires-Dist: munch
Requires-Dist: websockets
Dynamic: classifier
Dynamic: requires-dist
Dynamic: summary
